setup.py
centralsession/__init__.py
centralsession/backend.py
centralsession/django_session.py
centralsession/flask_session.py
centralsession/version.py
centralsession.egg-info/PKG-INFO
centralsession.egg-info/SOURCES.txt
centralsession.egg-info/dependency_links.txt
centralsession.egg-info/entry_points.txt
centralsession.egg-info/top_level.txt
tests/__init__.py
tests/base.py
tests/dj_settings.py
tests/test_backend.py
tests/test_django.py
tests/test_flask.py
tests/test_version.py
tests/djmirror/__init__.py
tests/djmirror/custom_db_backend.py
tests/djmirror/session_test.py