Metadata-Version: 1.1
Name: centralsession
Version: 0.3.0
Summary: A redis based session storage that works for flask and django
Home-page: https://github.com/pnegahdar/centralsessions
Author: Parham Negahdar
Author-email: pnegahdar@gmail.com
License: MIT
Keywords: flask django sessions session central
Platform: UNKNOWN
Classifier: Development Status :: 4 - Beta
Classifier: Intended Audience :: Developers
Classifier: License :: OSI Approved :: MIT License
Classifier: Natural Language :: English
Classifier: Operating System :: Unix
Classifier: Programming Language :: Python :: 2.7
Classifier: Operating System :: OS Independent
